[ { "category" : 26, "class" : 0, "desc" : "미드가르드", "enable_divide_sky" : 0, "id" : 260000001, "kind" : 0, "map_name" : "midgard", "particle_filename_0" : "1_mid_2_b_324", "particle_filename_1" : "1_mid_2_s_262", "particle_filename_2" : "empty", "particle_filename_3" : "empty", "particle_filename_4" : "empty", "particle_layer_index_0" : 2, "particle_layer_index_1" : 2, "particle_layer_index_2" : 0, "particle_layer_index_3" : 0, "particle_layer_index_4" : 0, "particle_pos_x_0" : 0, "particle_pos_x_1" : 0, "particle_pos_x_2" : 0, "particle_pos_x_3" : 0, "particle_pos_x_4" : 0, "particle_pos_y_0" : 324, "particle_pos_y_1" : 262, "particle_pos_y_2" : 0, "particle_pos_y_3" : 0, "particle_pos_y_4" : 0, "particle_z_order_0" : 82, "particle_z_order_1" : 82, "particle_z_order_2" : 0, "particle_z_order_3" : 0, "particle_z_order_4" : 0, "sky_back_count" : 0, "sky_count" : 6, "sky_front_count" : 0, "sky_y" : 104, "type" : 1, "use_particle_count" : 2 }
, { "category" : 26, "class" : 0, "desc" : "알프헤임 - 1차 배경", "enable_divide_sky" : 0, "id" : 260000002, "kind" : 0, "map_name" : "alfheim_1", "particle_filename_0" : "2_alf_r_52", "particle_filename_1" : "2_alf_r_368", "particle_filename_2" : "empty", "particle_filename_3" : "empty", "particle_filename_4" : "empty", "particle_layer_index_0" : 2, "particle_layer_index_1" : 2, "particle_layer_index_2" : 0, "particle_layer_index_3" : 0, "particle_layer_index_4" : 0, "particle_pos_x_0" : 0, "particle_pos_x_1" : 0, "particle_pos_x_2" : 0, "particle_pos_x_3" : 0, "particle_pos_x_4" : 0, "particle_pos_y_0" : 62, "particle_pos_y_1" : 368, "particle_pos_y_2" : 0, "particle_pos_y_3" : 0, "particle_pos_y_4" : 0, "particle_z_order_0" : 82, "particle_z_order_1" : 82, "particle_z_order_2" : 0, "particle_z_order_3" : 0, "particle_z_order_4" : 0, "sky_back_count" : 0, "sky_count" : 3, "sky_front_count" : 0, "sky_y" : 83, "type" : 2, "use_particle_count" : 2 }
, { "category" : 26, "class" : 0, "desc" : "스바르탈헤임 - 1차 배경", "enable_divide_sky" : 0, "id" : 260000003, "kind" : 0, "map_name" : "svartalfheim_1", "particle_filename_0" : "3_sva_b_340", "particle_filename_1" : "3_sva_s_364", "particle_filename_2" : "empty", "particle_filename_3" : "empty", "particle_filename_4" : "empty", "particle_layer_index_0" : 2, "particle_layer_index_1" : 1, "particle_layer_index_2" : 0, "particle_layer_index_3" : 0, "particle_layer_index_4" : 0, "particle_pos_x_0" : 0, "particle_pos_x_1" : 0, "particle_pos_x_2" : 0, "particle_pos_x_3" : 0, "particle_pos_x_4" : 0, "particle_pos_y_0" : 340, "particle_pos_y_1" : 364, "particle_pos_y_2" : 0, "particle_pos_y_3" : 0, "particle_pos_y_4" : 0, "particle_z_order_0" : 82, "particle_z_order_1" : 82, "particle_z_order_2" : 0, "particle_z_order_3" : 0, "particle_z_order_4" : 0, "sky_back_count" : 0, "sky_count" : 1, "sky_front_count" : 0, "sky_y" : 113.5, "type" : 3, "use_particle_count" : 2 }
, { "category" : 26, "class" : 0, "desc" : "니다벨리르 - 1차 배경", "enable_divide_sky" : 0, "id" : 260000004, "kind" : 0, "map_name" : "nadavellir_1", "particle_filename_0" : "4_nad_bs_344", "particle_filename_1" : "4_nad_ss_334", "particle_filename_2" : "empty", "particle_filename_3" : "empty", "particle_filename_4" : "empty", "particle_layer_index_0" : 2, "particle_layer_index_1" : 2, "particle_layer_index_2" : 0, "particle_layer_index_3" : 0, "particle_layer_index_4" : 0, "particle_pos_x_0" : 0, "particle_pos_x_1" : 0, "particle_pos_x_2" : 0, "particle_pos_x_3" : 0, "particle_pos_x_4" : 0, "particle_pos_y_0" : 344, "particle_pos_y_1" : 334, "particle_pos_y_2" : 0, "particle_pos_y_3" : 0, "particle_pos_y_4" : 0, "particle_z_order_0" : 82, "particle_z_order_1" : 82, "particle_z_order_2" : 0, "particle_z_order_3" : 0, "particle_z_order_4" : 0, "sky_back_count" : 0, "sky_count" : 1, "sky_front_count" : 0, "sky_y" : 116, "type" : 4, "use_particle_count" : 2 }
, { "category" : 26, "class" : 0, "desc" : "요툰헤임 - 1차 배경", "enable_divide_sky" : 0, "id" : 260000005, "kind" : 0, "map_name" : "jotunheim_1", "particle_filename_0" : "5_jo_sm_-72", "particle_filename_1" : "5_jo_sn_354", "particle_filename_2" : "empty", "particle_filename_3" : "empty", "particle_filename_4" : "empty", "particle_layer_index_0" : 2, "particle_layer_index_1" : 2, "particle_layer_index_2" : 0, "particle_layer_index_3" : 0, "particle_layer_index_4" : 0, "particle_pos_x_0" : 0, "particle_pos_x_1" : 0, "particle_pos_x_2" : 0, "particle_pos_x_3" : 0, "particle_pos_x_4" : 0, "particle_pos_y_0" : -72, "particle_pos_y_1" : 354, "particle_pos_y_2" : 0, "particle_pos_y_3" : 0, "particle_pos_y_4" : 0, "particle_z_order_0" : 82, "particle_z_order_1" : 82, "particle_z_order_2" : 0, "particle_z_order_3" : 0, "particle_z_order_4" : 0, "sky_back_count" : 0, "sky_count" : 2, "sky_front_count" : 0, "sky_y" : 120.5, "type" : 5, "use_particle_count" : 2 }
, { "category" : 26, "class" : 0, "desc" : "무스펠헤임 - 1차 배경", "enable_divide_sky" : 0, "id" : 260000006, "kind" : 0, "map_name" : "muspellheim_1", "particle_filename_0" : "6_mus_f_-4", "particle_filename_1" : "6_mus_sm_-58", "particle_filename_2" : "empty", "particle_filename_3" : "empty", "particle_filename_4" : "empty", "particle_layer_index_0" : 2, "particle_layer_index_1" : 2, "particle_layer_index_2" : 0, "particle_layer_index_3" : 0, "particle_layer_index_4" : 0, "particle_pos_x_0" : 0, "particle_pos_x_1" : 0, "particle_pos_x_2" : 0, "particle_pos_x_3" : 0, "particle_pos_x_4" : 0, "particle_pos_y_0" : -4, "particle_pos_y_1" : -58, "particle_pos_y_2" : 0, "particle_pos_y_3" : 0, "particle_pos_y_4" : 0, "particle_z_order_0" : 82, "particle_z_order_1" : 82, "particle_z_order_2" : 0, "particle_z_order_3" : 0, "particle_z_order_4" : 0, "sky_back_count" : 0, "sky_count" : 1, "sky_front_count" : 0, "sky_y" : 123.5, "type" : 6, "use_particle_count" : 2 }
, { "category" : 26, "class" : 0, "desc" : "바나헤임 - 1차 배경", "enable_divide_sky" : 0, "id" : 260000007, "kind" : 0, "map_name" : "vanaheim_1", "particle_filename_0" : "7_va_s_328", "particle_filename_1" : "7_va_s_350", "particle_filename_2" : "empty", "particle_filename_3" : "empty", "particle_filename_4" : "empty", "particle_layer_index_0" : 2, "particle_layer_index_1" : 2, "particle_layer_index_2" : 0, "particle_layer_index_3" : 0, "particle_layer_index_4" : 0, "particle_pos_x_0" : 0, "particle_pos_x_1" : 0, "particle_pos_x_2" : 0, "particle_pos_x_3" : 0, "particle_pos_x_4" : 0, "particle_pos_y_0" : 328, "particle_pos_y_1" : 350, "particle_pos_y_2" : 0, "particle_pos_y_3" : 0, "particle_pos_y_4" : 0, "particle_z_order_0" : 82, "particle_z_order_1" : 82, "particle_z_order_2" : 0, "particle_z_order_3" : 0, "particle_z_order_4" : 0, "sky_back_count" : 0, "sky_count" : 1, "sky_front_count" : 0, "sky_y" : 110.5, "type" : 7, "use_particle_count" : 2 }
, { "category" : 26, "class" : 0, "desc" : "니플헤임 - 1차 배경", "enable_divide_sky" : 0, "id" : 260000008, "kind" : 0, "map_name" : "niflheim_1", "particle_filename_0" : "8_ni_bf_-12", "particle_filename_1" : "8_ni_sf_188", "particle_filename_2" : "8_ni_s_-58", "particle_filename_3" : "empty", "particle_filename_4" : "empty", "particle_layer_index_0" : 2, "particle_layer_index_1" : 2, "particle_layer_index_2" : 2, "particle_layer_index_3" : 0, "particle_layer_index_4" : 0, "particle_pos_x_0" : 0, "particle_pos_x_1" : 0, "particle_pos_x_2" : 0, "particle_pos_x_3" : 0, "particle_pos_x_4" : 0, "particle_pos_y_0" : -12, "particle_pos_y_1" : 188, "particle_pos_y_2" : -58, "particle_pos_y_3" : 0, "particle_pos_y_4" : 0, "particle_z_order_0" : 82, "particle_z_order_1" : 82, "particle_z_order_2" : 82, "particle_z_order_3" : 0, "particle_z_order_4" : 0, "sky_back_count" : 0, "sky_count" : 1, "sky_front_count" : 0, "sky_y" : 122.5, "type" : 8, "use_particle_count" : 3 }
, { "category" : 26, "class" : 0, "desc" : "아스가르드 - 1차 배경", "enable_divide_sky" : 0, "id" : 260000009, "kind" : 0, "map_name" : "asgard_1", "particle_filename_0" : "9_as_p_240", "particle_filename_1" : "empty", "particle_filename_2" : "empty", "particle_filename_3" : "empty", "particle_filename_4" : "empty", "particle_layer_index_0" : 2, "particle_layer_index_1" : 0, "particle_layer_index_2" : 0, "particle_layer_index_3" : 0, "particle_layer_index_4" : 0, "particle_pos_x_0" : 0, "particle_pos_x_1" : 0, "particle_pos_x_2" : 0, "particle_pos_x_3" : 0, "particle_pos_x_4" : 0, "particle_pos_y_0" : 240, "particle_pos_y_1" : 0, "particle_pos_y_2" : 0, "particle_pos_y_3" : 0, "particle_pos_y_4" : 0, "particle_z_order_0" : 82, "particle_z_order_1" : 0, "particle_z_order_2" : 0, "particle_z_order_3" : 0, "particle_z_order_4" : 0, "sky_back_count" : 0, "sky_count" : 1, "sky_front_count" : 0, "sky_y" : 102, "type" : 9, "use_particle_count" : 1 }
, { "category" : 26, "class" : 0, "desc" : "사용안함", "enable_divide_sky" : 0, "id" : 260000010, "kind" : 0, "map_name" : "berserkzone", "particle_filename_0" : "empty", "particle_filename_1" : "empty", "particle_filename_2" : "empty", "particle_filename_3" : "empty", "particle_filename_4" : "empty", "particle_layer_index_0" : 0, "particle_layer_index_1" : 0, "particle_layer_index_2" : 0, "particle_layer_index_3" : 0, "particle_layer_index_4" : 0, "particle_pos_x_0" : 0, "particle_pos_x_1" : 0, "particle_pos_x_2" : 0, "particle_pos_x_3" : 0, "particle_pos_x_4" : 0, "particle_pos_y_0" : 0, "particle_pos_y_1" : 0, "particle_pos_y_2" : 0, "particle_pos_y_3" : 0, "particle_pos_y_4" : 0, "particle_z_order_0" : 0, "particle_z_order_1" : 0, "particle_z_order_2" : 0, "particle_z_order_3" : 0, "particle_z_order_4" : 0, "sky_back_count" : 0, "sky_count" : 0, "sky_front_count" : 0, "sky_y" : 107.5, "type" : 10, "use_particle_count" : 0 }
, { "category" : 26, "class" : 0, "desc" : "프롤로그", "enable_divide_sky" : 0, "id" : 260000011, "kind" : 0, "map_name" : "jormungandzone", "particle_filename_0" : "empty", "particle_filename_1" : "empty", "particle_filename_2" : "empty", "particle_filename_3" : "empty", "particle_filename_4" : "empty", "particle_layer_index_0" : 0, "particle_layer_index_1" : 0, "particle_layer_index_2" : 0, "particle_layer_index_3" : 0, "particle_layer_index_4" : 0, "particle_pos_x_0" : 0, "particle_pos_x_1" : 0, "particle_pos_x_2" : 0, "particle_pos_x_3" : 0, "particle_pos_x_4" : 0, "particle_pos_y_0" : 0, "particle_pos_y_1" : 0, "particle_pos_y_2" : 0, "particle_pos_y_3" : 0, "particle_pos_y_4" : 0, "particle_z_order_0" : 0, "particle_z_order_1" : 0, "particle_z_order_2" : 0, "particle_z_order_3" : 0, "particle_z_order_4" : 0, "sky_back_count" : 0, "sky_count" : 0, "sky_front_count" : 0, "sky_y" : 115, "type" : 11, "use_particle_count" : 0 }
, { "category" : 26, "class" : 0, "desc" : "수호신의 신전", "enable_divide_sky" : 0, "id" : 260000012, "kind" : 0, "map_name" : "valhalla", "particle_filename_0" : "empty", "particle_filename_1" : "empty", "particle_filename_2" : "empty", "particle_filename_3" : "empty", "particle_filename_4" : "empty", "particle_layer_index_0" : 0, "particle_layer_index_1" : 0, "particle_layer_index_2" : 0, "particle_layer_index_3" : 0, "particle_layer_index_4" : 0, "particle_pos_x_0" : 0, "particle_pos_x_1" : 0, "particle_pos_x_2" : 0, "particle_pos_x_3" : 0, "particle_pos_x_4" : 0, "particle_pos_y_0" : 0, "particle_pos_y_1" : 0, "particle_pos_y_2" : 0, "particle_pos_y_3" : 0, "particle_pos_y_4" : 0, "particle_z_order_0" : 0, "particle_z_order_1" : 0, "particle_z_order_2" : 0, "particle_z_order_3" : 0, "particle_z_order_4" : 0, "sky_back_count" : 0, "sky_count" : 0, "sky_front_count" : 0, "sky_y" : 99, "type" : 12, "use_particle_count" : 0 }
, { "category" : 26, "class" : 1, "desc" : "아레나", "enable_divide_sky" : 0, "id" : 260001013, "kind" : 0, "map_name" : "arena", "particle_filename_0" : "empty", "particle_filename_1" : "empty", "particle_filename_2" : "empty", "particle_filename_3" : "empty", "particle_filename_4" : "empty", "particle_layer_index_0" : 0, "particle_layer_index_1" : 0, "particle_layer_index_2" : 0, "particle_layer_index_3" : 0, "particle_layer_index_4" : 0, "particle_pos_x_0" : 0, "particle_pos_x_1" : 0, "particle_pos_x_2" : 0, "particle_pos_x_3" : 0, "particle_pos_x_4" : 0, "particle_pos_y_0" : 0, "particle_pos_y_1" : 0, "particle_pos_y_2" : 0, "particle_pos_y_3" : 0, "particle_pos_y_4" : 0, "particle_z_order_0" : 0, "particle_z_order_1" : 0, "particle_z_order_2" : 0, "particle_z_order_3" : 0, "particle_z_order_4" : 0, "sky_back_count" : 0, "sky_count" : 0, "sky_front_count" : 0, "sky_y" : 0, "type" : 13, "use_particle_count" : 0 }
, { "category" : 26, "class" : 1, "desc" : "월드보스", "enable_divide_sky" : 0, "id" : 260001014, "kind" : 0, "map_name" : "nidhoggzone", "particle_filename_0" : "empty", "particle_filename_1" : "empty", "particle_filename_2" : "empty", "particle_filename_3" : "empty", "particle_filename_4" : "empty", "particle_layer_index_0" : 0, "particle_layer_index_1" : 0, "particle_layer_index_2" : 0, "particle_layer_index_3" : 0, "particle_layer_index_4" : 0, "particle_pos_x_0" : 0, "particle_pos_x_1" : 0, "particle_pos_x_2" : 0, "particle_pos_x_3" : 0, "particle_pos_x_4" : 0, "particle_pos_y_0" : 0, "particle_pos_y_1" : 0, "particle_pos_y_2" : 0, "particle_pos_y_3" : 0, "particle_pos_y_4" : 0, "particle_z_order_0" : 0, "particle_z_order_1" : 0, "particle_z_order_2" : 0, "particle_z_order_3" : 0, "particle_z_order_4" : 0, "sky_back_count" : 0, "sky_count" : 0, "sky_front_count" : 0, "sky_y" : 0, "type" : 14, "use_particle_count" : 0 }
, { "category" : 26, "class" : 1, "desc" : "공성전(비전투)", "enable_divide_sky" : 0, "id" : 260001015, "kind" : 0, "map_name" : "multi", "particle_filename_0" : "empty", "particle_filename_1" : "empty", "particle_filename_2" : "empty", "particle_filename_3" : "empty", "particle_filename_4" : "empty", "particle_layer_index_0" : 0, "particle_layer_index_1" : 0, "particle_layer_index_2" : 0, "particle_layer_index_3" : 0, "particle_layer_index_4" : 0, "particle_pos_x_0" : 0, "particle_pos_x_1" : 0, "particle_pos_x_2" : 0, "particle_pos_x_3" : 0, "particle_pos_x_4" : 0, "particle_pos_y_0" : 0, "particle_pos_y_1" : 0, "particle_pos_y_2" : 0, "particle_pos_y_3" : 0, "particle_pos_y_4" : 0, "particle_z_order_0" : 0, "particle_z_order_1" : 0, "particle_z_order_2" : 0, "particle_z_order_3" : 0, "particle_z_order_4" : 0, "sky_back_count" : 0, "sky_count" : 0, "sky_front_count" : 0, "sky_y" : 91, "type" : 15, "use_particle_count" : 0 }
, { "category" : 26, "class" : 1, "desc" : "공성전(전투)", "enable_divide_sky" : 0, "id" : 260001016, "kind" : 0, "map_name" : "multi_combat", "particle_filename_0" : "empty", "particle_filename_1" : "empty", "particle_filename_2" : "empty", "particle_filename_3" : "empty", "particle_filename_4" : "empty", "particle_layer_index_0" : 0, "particle_layer_index_1" : 0, "particle_layer_index_2" : 0, "particle_layer_index_3" : 0, "particle_layer_index_4" : 0, "particle_pos_x_0" : 0, "particle_pos_x_1" : 0, "particle_pos_x_2" : 0, "particle_pos_x_3" : 0, "particle_pos_x_4" : 0, "particle_pos_y_0" : 0, "particle_pos_y_1" : 0, "particle_pos_y_2" : 0, "particle_pos_y_3" : 0, "particle_pos_y_4" : 0, "particle_z_order_0" : 0, "particle_z_order_1" : 0, "particle_z_order_2" : 0, "particle_z_order_3" : 0, "particle_z_order_4" : 0, "sky_back_count" : 0, "sky_count" : 0, "sky_front_count" : 0, "sky_y" : 91, "type" : 16, "use_particle_count" : 0 }
, { "category" : 26, "class" : 0, "desc" : "수호신의 신전(프레이야)", "enable_divide_sky" : 0, "id" : 260001017, "kind" : 0, "map_name" : "preyja_cave", "particle_filename_0" : "freyja_-14", "particle_filename_1" : "empty", "particle_filename_2" : "empty", "particle_filename_3" : "empty", "particle_filename_4" : "empty", "particle_layer_index_0" : 1, "particle_layer_index_1" : 0, "particle_layer_index_2" : 0, "particle_layer_index_3" : 0, "particle_layer_index_4" : 0, "particle_pos_x_0" : 0, "particle_pos_x_1" : 0, "particle_pos_x_2" : 0, "particle_pos_x_3" : 0, "particle_pos_x_4" : 0, "particle_pos_y_0" : 96, "particle_pos_y_1" : 0, "particle_pos_y_2" : 0, "particle_pos_y_3" : 0, "particle_pos_y_4" : 0, "particle_z_order_0" : 82, "particle_z_order_1" : 0, "particle_z_order_2" : 0, "particle_z_order_3" : 0, "particle_z_order_4" : 0, "sky_back_count" : 0, "sky_count" : 0, "sky_front_count" : 0, "sky_y" : 95, "type" : 17, "use_particle_count" : 1 }
, { "category" : 26, "class" : 0, "desc" : "수호신의 신전(헤임달)", "enable_divide_sky" : 0, "id" : 260001018, "kind" : 0, "map_name" : "heimdallr_cave", "particle_filename_0" : "heimdal_336", "particle_filename_1" : "empty", "particle_filename_2" : "empty", "particle_filename_3" : "empty", "particle_filename_4" : "empty", "particle_layer_index_0" : 2, "particle_layer_index_1" : 0, "particle_layer_index_2" : 0, "particle_layer_index_3" : 0, "particle_layer_index_4" : 0, "particle_pos_x_0" : 0, "particle_pos_x_1" : 0, "particle_pos_x_2" : 0, "particle_pos_x_3" : 0, "particle_pos_x_4" : 0, "particle_pos_y_0" : 336, "particle_pos_y_1" : 0, "particle_pos_y_2" : 0, "particle_pos_y_3" : 0, "particle_pos_y_4" : 0, "particle_z_order_0" : 82, "particle_z_order_1" : 0, "particle_z_order_2" : 0, "particle_z_order_3" : 0, "particle_z_order_4" : 0, "sky_back_count" : 0, "sky_count" : 0, "sky_front_count" : 0, "sky_y" : 0, "type" : 18, "use_particle_count" : 1 }
, { "category" : 26, "class" : 0, "desc" : "수호신의 신전(프레이르)", "enable_divide_sky" : 0, "id" : 260001019, "kind" : 0, "map_name" : "freyr_cave", "particle_filename_0" : "freyr_313", "particle_filename_1" : "empty", "particle_filename_2" : "empty", "particle_filename_3" : "empty", "particle_filename_4" : "empty", "particle_layer_index_0" : 4, "particle_layer_index_1" : 0, "particle_layer_index_2" : 0, "particle_layer_index_3" : 0, "particle_layer_index_4" : 0, "particle_pos_x_0" : 0, "particle_pos_x_1" : 0, "particle_pos_x_2" : 0, "particle_pos_x_3" : 0, "particle_pos_x_4" : 0, "particle_pos_y_0" : 330, "particle_pos_y_1" : 0, "particle_pos_y_2" : 0, "particle_pos_y_3" : 0, "particle_pos_y_4" : 0, "particle_z_order_0" : 82, "particle_z_order_1" : 0, "particle_z_order_2" : 0, "particle_z_order_3" : 0, "particle_z_order_4" : 0, "sky_back_count" : 0, "sky_count" : 0, "sky_front_count" : 0, "sky_y" : 90.5, "type" : 19, "use_particle_count" : 1 }
, { "category" : 26, "class" : 0, "desc" : "수호신의 신전(엘룬)", "enable_divide_sky" : 0, "id" : 260001020, "kind" : 0, "map_name" : "elune_cave", "particle_filename_0" : "empty", "particle_filename_1" : "empty", "particle_filename_2" : "empty", "particle_filename_3" : "empty", "particle_filename_4" : "empty", "particle_layer_index_0" : 0, "particle_layer_index_1" : 0, "particle_layer_index_2" : 0, "particle_layer_index_3" : 0, "particle_layer_index_4" : 0, "particle_pos_x_0" : 0, "particle_pos_x_1" : 0, "particle_pos_x_2" : 0, "particle_pos_x_3" : 0, "particle_pos_x_4" : 0, "particle_pos_y_0" : 0, "particle_pos_y_1" : 0, "particle_pos_y_2" : 0, "particle_pos_y_3" : 0, "particle_pos_y_4" : 0, "particle_z_order_0" : 0, "particle_z_order_1" : 0, "particle_z_order_2" : 0, "particle_z_order_3" : 0, "particle_z_order_4" : 0, "sky_back_count" : 0, "sky_count" : 0, "sky_front_count" : 0, "sky_y" : 94, "type" : 20, "use_particle_count" : 0 }
, { "category" : 26, "class" : 0, "desc" : "수호신의 신전(티르1)", "enable_divide_sky" : 0, "id" : 260001021, "kind" : 0, "map_name" : "tyr_cave_1", "particle_filename_0" : "tyr_340", "particle_filename_1" : "tyr_412", "particle_filename_2" : "empty", "particle_filename_3" : "empty", "particle_filename_4" : "empty", "particle_layer_index_0" : 2, "particle_layer_index_1" : 2, "particle_layer_index_2" : 0, "particle_layer_index_3" : 0, "particle_layer_index_4" : 0, "particle_pos_x_0" : 0, "particle_pos_x_1" : 0, "particle_pos_x_2" : 0, "particle_pos_x_3" : 0, "particle_pos_x_4" : 0, "particle_pos_y_0" : 340, "particle_pos_y_1" : 412, "particle_pos_y_2" : 0, "particle_pos_y_3" : 0, "particle_pos_y_4" : 0, "particle_z_order_0" : 82, "particle_z_order_1" : 82, "particle_z_order_2" : 0, "particle_z_order_3" : 0, "particle_z_order_4" : 0, "sky_back_count" : 0, "sky_count" : 0, "sky_front_count" : 0, "sky_y" : 98.5, "type" : 21, "use_particle_count" : 2 }
, { "category" : 26, "class" : 0, "desc" : "수호신의 신전(티르2)", "enable_divide_sky" : 0, "id" : 260001022, "kind" : 0, "map_name" : "tyr_cave_2", "particle_filename_0" : "tyr_340", "particle_filename_1" : "tyr_412", "particle_filename_2" : "empty", "particle_filename_3" : "empty", "particle_filename_4" : "empty", "particle_layer_index_0" : 2, "particle_layer_index_1" : 2, "particle_layer_index_2" : 0, "particle_layer_index_3" : 0, "particle_layer_index_4" : 0, "particle_pos_x_0" : 0, "particle_pos_x_1" : 0, "particle_pos_x_2" : 0, "particle_pos_x_3" : 0, "particle_pos_x_4" : 0, "particle_pos_y_0" : 340, "particle_pos_y_1" : 412, "particle_pos_y_2" : 0, "particle_pos_y_3" : 0, "particle_pos_y_4" : 0, "particle_z_order_0" : 82, "particle_z_order_1" : 82, "particle_z_order_2" : 0, "particle_z_order_3" : 0, "particle_z_order_4" : 0, "sky_back_count" : 0, "sky_count" : 0, "sky_front_count" : 0, "sky_y" : 98.5, "type" : 22, "use_particle_count" : 2 }
, { "category" : 26, "class" : 0, "desc" : "수호신의 신전(토르1)", "enable_divide_sky" : 0, "id" : 260001023, "kind" : 0, "map_name" : "thor_cave_1", "particle_filename_0" : "thor_1_186", "particle_filename_1" : "empty", "particle_filename_2" : "empty", "particle_filename_3" : "empty", "particle_filename_4" : "empty", "particle_layer_index_0" : 2, "particle_layer_index_1" : 0, "particle_layer_index_2" : 0, "particle_layer_index_3" : 0, "particle_layer_index_4" : 0, "particle_pos_x_0" : 0, "particle_pos_x_1" : 0, "particle_pos_x_2" : 0, "particle_pos_x_3" : 0, "particle_pos_x_4" : 0, "particle_pos_y_0" : 336, "particle_pos_y_1" : 0, "particle_pos_y_2" : 0, "particle_pos_y_3" : 0, "particle_pos_y_4" : 0, "particle_z_order_0" : 78, "particle_z_order_1" : 0, "particle_z_order_2" : 0, "particle_z_order_3" : 0, "particle_z_order_4" : 0, "sky_back_count" : 0, "sky_count" : 0, "sky_front_count" : 0, "sky_y" : 91, "type" : 23, "use_particle_count" : 1 }
, { "category" : 26, "class" : 0, "desc" : "수호신의 신전(토르2)", "enable_divide_sky" : 0, "id" : 260001024, "kind" : 0, "map_name" : "thor_cave_2", "particle_filename_0" : "thor_1_186", "particle_filename_1" : "empty", "particle_filename_2" : "empty", "particle_filename_3" : "empty", "particle_filename_4" : "empty", "particle_layer_index_0" : 2, "particle_layer_index_1" : 0, "particle_layer_index_2" : 0, "particle_layer_index_3" : 0, "particle_layer_index_4" : 0, "particle_pos_x_0" : 0, "particle_pos_x_1" : 0, "particle_pos_x_2" : 0, "particle_pos_x_3" : 0, "particle_pos_x_4" : 0, "particle_pos_y_0" : 336, "particle_pos_y_1" : 0, "particle_pos_y_2" : 0, "particle_pos_y_3" : 0, "particle_pos_y_4" : 0, "particle_z_order_0" : 78, "particle_z_order_1" : 0, "particle_z_order_2" : 0, "particle_z_order_3" : 0, "particle_z_order_4" : 0, "sky_back_count" : 0, "sky_count" : 0, "sky_front_count" : 0, "sky_y" : 91, "type" : 24, "use_particle_count" : 1 }
, { "category" : 26, "class" : 0, "desc" : "트롤 전용 맵(구 아스가르드)", "enable_divide_sky" : 0, "id" : 260001025, "kind" : 0, "map_name" : "troll", "particle_filename_0" : "empty", "particle_filename_1" : "empty", "particle_filename_2" : "empty", "particle_filename_3" : "empty", "particle_filename_4" : "empty", "particle_layer_index_0" : 0, "particle_layer_index_1" : 0, "particle_layer_index_2" : 0, "particle_layer_index_3" : 0, "particle_layer_index_4" : 0, "particle_pos_x_0" : 0, "particle_pos_x_1" : 0, "particle_pos_x_2" : 0, "particle_pos_x_3" : 0, "particle_pos_x_4" : 0, "particle_pos_y_0" : 0, "particle_pos_y_1" : 0, "particle_pos_y_2" : 0, "particle_pos_y_3" : 0, "particle_pos_y_4" : 0, "particle_z_order_0" : 0, "particle_z_order_1" : 0, "particle_z_order_2" : 0, "particle_z_order_3" : 0, "particle_z_order_4" : 0, "sky_back_count" : 0, "sky_count" : 0, "sky_front_count" : 0, "sky_y" : 102, "type" : 25, "use_particle_count" : 0 }
, { "category" : 26, "class" : 0, "desc" : "길드레이드", "enable_divide_sky" : 1, "id" : 260001026, "kind" : 0, "map_name" : "guildraid", "particle_filename_0" : "empty", "particle_filename_1" : "empty", "particle_filename_2" : "empty", "particle_filename_3" : "empty", "particle_filename_4" : "empty", "particle_layer_index_0" : 0, "particle_layer_index_1" : 0, "particle_layer_index_2" : 0, "particle_layer_index_3" : 0, "particle_layer_index_4" : 0, "particle_pos_x_0" : 0, "particle_pos_x_1" : 0, "particle_pos_x_2" : 0, "particle_pos_x_3" : 0, "particle_pos_x_4" : 0, "particle_pos_y_0" : 0, "particle_pos_y_1" : 0, "particle_pos_y_2" : 0, "particle_pos_y_3" : 0, "particle_pos_y_4" : 0, "particle_z_order_0" : 0, "particle_z_order_1" : 0, "particle_z_order_2" : 0, "particle_z_order_3" : 0, "particle_z_order_4" : 0, "sky_back_count" : 2, "sky_count" : 1, "sky_front_count" : 0, "sky_y" : 0, "type" : 26, "use_particle_count" : 0 }
, { "category" : 26, "class" : 0, "desc" : "요일보스 - 월요일", "enable_divide_sky" : 0, "id" : 260001027, "kind" : 0, "map_name" : "jormungandzone", "particle_filename_0" : "empty", "particle_filename_1" : "empty", "particle_filename_2" : "empty", "particle_filename_3" : "empty", "particle_filename_4" : "empty", "particle_layer_index_0" : 0, "particle_layer_index_1" : 0, "particle_layer_index_2" : 0, "particle_layer_index_3" : 0, "particle_layer_index_4" : 0, "particle_pos_x_0" : 0, "particle_pos_x_1" : 0, "particle_pos_x_2" : 0, "particle_pos_x_3" : 0, "particle_pos_x_4" : 0, "particle_pos_y_0" : 0, "particle_pos_y_1" : 0, "particle_pos_y_2" : 0, "particle_pos_y_3" : 0, "particle_pos_y_4" : 0, "particle_z_order_0" : 0, "particle_z_order_1" : 0, "particle_z_order_2" : 0, "particle_z_order_3" : 0, "particle_z_order_4" : 0, "sky_back_count" : 0, "sky_count" : 0, "sky_front_count" : 0, "sky_y" : 115, "type" : 27, "use_particle_count" : 0 }
, { "category" : 26, "class" : 0, "desc" : "요일보스 - 화요일", "enable_divide_sky" : 0, "id" : 260001028, "kind" : 0, "map_name" : "muspellheim", "particle_filename_0" : "empty", "particle_filename_1" : "empty", "particle_filename_2" : "empty", "particle_filename_3" : "empty", "particle_filename_4" : "empty", "particle_layer_index_0" : 0, "particle_layer_index_1" : 0, "particle_layer_index_2" : 0, "particle_layer_index_3" : 0, "particle_layer_index_4" : 0, "particle_pos_x_0" : 0, "particle_pos_x_1" : 0, "particle_pos_x_2" : 0, "particle_pos_x_3" : 0, "particle_pos_x_4" : 0, "particle_pos_y_0" : 0, "particle_pos_y_1" : 0, "particle_pos_y_2" : 0, "particle_pos_y_3" : 0, "particle_pos_y_4" : 0, "particle_z_order_0" : 0, "particle_z_order_1" : 0, "particle_z_order_2" : 0, "particle_z_order_3" : 0, "particle_z_order_4" : 0, "sky_back_count" : 0, "sky_count" : 0, "sky_front_count" : 0, "sky_y" : 123.5, "type" : 28, "use_particle_count" : 0 }
, { "category" : 26, "class" : 0, "desc" : "요일보스 - 수요일", "enable_divide_sky" : 0, "id" : 260001029, "kind" : 0, "map_name" : "jormungandzone", "particle_filename_0" : "empty", "particle_filename_1" : "empty", "particle_filename_2" : "empty", "particle_filename_3" : "empty", "particle_filename_4" : "empty", "particle_layer_index_0" : 0, "particle_layer_index_1" : 0, "particle_layer_index_2" : 0, "particle_layer_index_3" : 0, "particle_layer_index_4" : 0, "particle_pos_x_0" : 0, "particle_pos_x_1" : 0, "particle_pos_x_2" : 0, "particle_pos_x_3" : 0, "particle_pos_x_4" : 0, "particle_pos_y_0" : 0, "particle_pos_y_1" : 0, "particle_pos_y_2" : 0, "particle_pos_y_3" : 0, "particle_pos_y_4" : 0, "particle_z_order_0" : 0, "particle_z_order_1" : 0, "particle_z_order_2" : 0, "particle_z_order_3" : 0, "particle_z_order_4" : 0, "sky_back_count" : 0, "sky_count" : 0, "sky_front_count" : 0, "sky_y" : 115, "type" : 29, "use_particle_count" : 0 }
, { "category" : 26, "class" : 0, "desc" : "요일보스 - 목요일", "enable_divide_sky" : 0, "id" : 260001030, "kind" : 0, "map_name" : "niflheim", "particle_filename_0" : "empty", "particle_filename_1" : "empty", "particle_filename_2" : "empty", "particle_filename_3" : "empty", "particle_filename_4" : "empty", "particle_layer_index_0" : 0, "particle_layer_index_1" : 0, "particle_layer_index_2" : 0, "particle_layer_index_3" : 0, "particle_layer_index_4" : 0, "particle_pos_x_0" : 0, "particle_pos_x_1" : 0, "particle_pos_x_2" : 0, "particle_pos_x_3" : 0, "particle_pos_x_4" : 0, "particle_pos_y_0" : 0, "particle_pos_y_1" : 0, "particle_pos_y_2" : 0, "particle_pos_y_3" : 0, "particle_pos_y_4" : 0, "particle_z_order_0" : 0, "particle_z_order_1" : 0, "particle_z_order_2" : 0, "particle_z_order_3" : 0, "particle_z_order_4" : 0, "sky_back_count" : 0, "sky_count" : 0, "sky_front_count" : 0, "sky_y" : 122.5, "type" : 30, "use_particle_count" : 0 }
, { "category" : 26, "class" : 0, "desc" : "요일보스 - 금요일", "enable_divide_sky" : 0, "id" : 260001031, "kind" : 0, "map_name" : "berserkzone", "particle_filename_0" : "empty", "particle_filename_1" : "empty", "particle_filename_2" : "empty", "particle_filename_3" : "empty", "particle_filename_4" : "empty", "particle_layer_index_0" : 0, "particle_layer_index_1" : 0, "particle_layer_index_2" : 0, "particle_layer_index_3" : 0, "particle_layer_index_4" : 0, "particle_pos_x_0" : 0, "particle_pos_x_1" : 0, "particle_pos_x_2" : 0, "particle_pos_x_3" : 0, "particle_pos_x_4" : 0, "particle_pos_y_0" : 0, "particle_pos_y_1" : 0, "particle_pos_y_2" : 0, "particle_pos_y_3" : 0, "particle_pos_y_4" : 0, "particle_z_order_0" : 0, "particle_z_order_1" : 0, "particle_z_order_2" : 0, "particle_z_order_3" : 0, "particle_z_order_4" : 0, "sky_back_count" : 0, "sky_count" : 0, "sky_front_count" : 0, "sky_y" : 107.5, "type" : 31, "use_particle_count" : 0 }
, { "category" : 26, "class" : 0, "desc" : "요일보스 - 토요일", "enable_divide_sky" : 0, "id" : 260001032, "kind" : 0, "map_name" : "berserkzone", "particle_filename_0" : "empty", "particle_filename_1" : "empty", "particle_filename_2" : "empty", "particle_filename_3" : "empty", "particle_filename_4" : "empty", "particle_layer_index_0" : 0, "particle_layer_index_1" : 0, "particle_layer_index_2" : 0, "particle_layer_index_3" : 0, "particle_layer_index_4" : 0, "particle_pos_x_0" : 0, "particle_pos_x_1" : 0, "particle_pos_x_2" : 0, "particle_pos_x_3" : 0, "particle_pos_x_4" : 0, "particle_pos_y_0" : 0, "particle_pos_y_1" : 0, "particle_pos_y_2" : 0, "particle_pos_y_3" : 0, "particle_pos_y_4" : 0, "particle_z_order_0" : 0, "particle_z_order_1" : 0, "particle_z_order_2" : 0, "particle_z_order_3" : 0, "particle_z_order_4" : 0, "sky_back_count" : 0, "sky_count" : 0, "sky_front_count" : 0, "sky_y" : 107.5, "type" : 32, "use_particle_count" : 0 }
, { "category" : 26, "class" : 0, "desc" : "요일보스 - 일요일", "enable_divide_sky" : 0, "id" : 260001033, "kind" : 0, "map_name" : "jormungandzone", "particle_filename_0" : "empty", "particle_filename_1" : "empty", "particle_filename_2" : "empty", "particle_filename_3" : "empty", "particle_filename_4" : "empty", "particle_layer_index_0" : 0, "particle_layer_index_1" : 0, "particle_layer_index_2" : 0, "particle_layer_index_3" : 0, "particle_layer_index_4" : 0, "particle_pos_x_0" : 0, "particle_pos_x_1" : 0, "particle_pos_x_2" : 0, "particle_pos_x_3" : 0, "particle_pos_x_4" : 0, "particle_pos_y_0" : 0, "particle_pos_y_1" : 0, "particle_pos_y_2" : 0, "particle_pos_y_3" : 0, "particle_pos_y_4" : 0, "particle_z_order_0" : 0, "particle_z_order_1" : 0, "particle_z_order_2" : 0, "particle_z_order_3" : 0, "particle_z_order_4" : 0, "sky_back_count" : 0, "sky_count" : 0, "sky_front_count" : 0, "sky_y" : 115, "type" : 33, "use_particle_count" : 0 }
, { "category" : 26, "class" : 0, "desc" : "알프헤임 - 2차 배경", "enable_divide_sky" : 1, "id" : 260000034, "kind" : 0, "map_name" : "alfheim_2", "particle_filename_0" : "2_alf_2_326", "particle_filename_1" : "2_alf_2_r_-76", "particle_filename_2" : "empty", "particle_filename_3" : "empty", "particle_filename_4" : "empty", "particle_layer_index_0" : 2, "particle_layer_index_1" : 2, "particle_layer_index_2" : 0, "particle_layer_index_3" : 0, "particle_layer_index_4" : 0, "particle_pos_x_0" : 0, "particle_pos_x_1" : 0, "particle_pos_x_2" : 0, "particle_pos_x_3" : 0, "particle_pos_x_4" : 0, "particle_pos_y_0" : 326, "particle_pos_y_1" : -76, "particle_pos_y_2" : 0, "particle_pos_y_3" : 0, "particle_pos_y_4" : 0, "particle_z_order_0" : 82, "particle_z_order_1" : 82, "particle_z_order_2" : 0, "particle_z_order_3" : 0, "particle_z_order_4" : 0, "sky_back_count" : 1, "sky_count" : 9, "sky_front_count" : 0, "sky_y" : 83, "type" : 34, "use_particle_count" : 2 }
, { "category" : 26, "class" : 0, "desc" : "스바르탈헤임 - 2차 배경", "enable_divide_sky" : 0, "id" : 260000035, "kind" : 0, "map_name" : "svartalfheim_2", "particle_filename_0" : "3_sva_2_b_-15", "particle_filename_1" : "3_sva_2_s_93", "particle_filename_2" : "empty", "particle_filename_3" : "empty", "particle_filename_4" : "empty", "particle_layer_index_0" : 2, "particle_layer_index_1" : 1, "particle_layer_index_2" : 0, "particle_layer_index_3" : 0, "particle_layer_index_4" : 0, "particle_pos_x_0" : 0, "particle_pos_x_1" : 0, "particle_pos_x_2" : 0, "particle_pos_x_3" : 0, "particle_pos_x_4" : 0, "particle_pos_y_0" : -15, "particle_pos_y_1" : 93, "particle_pos_y_2" : 0, "particle_pos_y_3" : 0, "particle_pos_y_4" : 0, "particle_z_order_0" : 82, "particle_z_order_1" : 82, "particle_z_order_2" : 0, "particle_z_order_3" : 0, "particle_z_order_4" : 0, "sky_back_count" : 0, "sky_count" : 1, "sky_front_count" : 0, "sky_y" : 113.5, "type" : 35, "use_particle_count" : 2 }
, { "category" : 26, "class" : 0, "desc" : "니다벨리르 - 2차 배경", "enable_divide_sky" : 1, "id" : 260000036, "kind" : 0, "map_name" : "nadavellir_2", "particle_filename_0" : "4_nad_2_bs_344", "particle_filename_1" : "4_nad_2_ss_334", "particle_filename_2" : "empty", "particle_filename_3" : "empty", "particle_filename_4" : "empty", "particle_layer_index_0" : 2, "particle_layer_index_1" : 2, "particle_layer_index_2" : 0, "particle_layer_index_3" : 0, "particle_layer_index_4" : 0, "particle_pos_x_0" : 0, "particle_pos_x_1" : 0, "particle_pos_x_2" : 0, "particle_pos_x_3" : 0, "particle_pos_x_4" : 0, "particle_pos_y_0" : 344, "particle_pos_y_1" : 334, "particle_pos_y_2" : 0, "particle_pos_y_3" : 0, "particle_pos_y_4" : 0, "particle_z_order_0" : 82, "particle_z_order_1" : 82, "particle_z_order_2" : 0, "particle_z_order_3" : 0, "particle_z_order_4" : 0, "sky_back_count" : 0, "sky_count" : 1, "sky_front_count" : 1, "sky_y" : 116, "type" : 36, "use_particle_count" : 2 }
, { "category" : 26, "class" : 0, "desc" : "요툰헤임 - 2차 배경", "enable_divide_sky" : 1, "id" : 260000037, "kind" : 0, "map_name" : "jotunheim_2", "particle_filename_0" : "5_jo_sm_-72", "particle_filename_1" : "5_jo_sn_354", "particle_filename_2" : "5_jo_2_sm_-111", "particle_filename_3" : "5_jo_2_sn_354", "particle_filename_4" : "empty", "particle_layer_index_0" : 2, "particle_layer_index_1" : 2, "particle_layer_index_2" : 2, "particle_layer_index_3" : 2, "particle_layer_index_4" : 0, "particle_pos_x_0" : 0, "particle_pos_x_1" : 0, "particle_pos_x_2" : 0, "particle_pos_x_3" : 0, "particle_pos_x_4" : 0, "particle_pos_y_0" : -72, "particle_pos_y_1" : 354, "particle_pos_y_2" : -111, "particle_pos_y_3" : 354, "particle_pos_y_4" : 0, "particle_z_order_0" : 82, "particle_z_order_1" : 82, "particle_z_order_2" : 82, "particle_z_order_3" : 82, "particle_z_order_4" : 0, "sky_back_count" : 1, "sky_count" : 1, "sky_front_count" : 0, "sky_y" : 120.5, "type" : 37, "use_particle_count" : 4 }
, { "category" : 26, "class" : 0, "desc" : "무스펠헤임 - 2차 배경", "enable_divide_sky" : 1, "id" : 260000038, "kind" : 0, "map_name" : "muspellheim_2", "particle_filename_0" : "6_mus_2_-6", "particle_filename_1" : "empty", "particle_filename_2" : "empty", "particle_filename_3" : "empty", "particle_filename_4" : "empty", "particle_layer_index_0" : 2, "particle_layer_index_1" : 0, "particle_layer_index_2" : 0, "particle_layer_index_3" : 0, "particle_layer_index_4" : 0, "particle_pos_x_0" : 0, "particle_pos_x_1" : 0, "particle_pos_x_2" : 0, "particle_pos_x_3" : 0, "particle_pos_x_4" : 0, "particle_pos_y_0" : -6, "particle_pos_y_1" : 0, "particle_pos_y_2" : 0, "particle_pos_y_3" : 0, "particle_pos_y_4" : 0, "particle_z_order_0" : 82, "particle_z_order_1" : 0, "particle_z_order_2" : 0, "particle_z_order_3" : 0, "particle_z_order_4" : 0, "sky_back_count" : 0, "sky_count" : 1, "sky_front_count" : 2, "sky_y" : 123.5, "type" : 38, "use_particle_count" : 1 }
, { "category" : 26, "class" : 0, "desc" : "바나헤임 - 2차 배경", "enable_divide_sky" : 1, "id" : 260000039, "kind" : 0, "map_name" : "vanaheim_2", "particle_filename_0" : "7_va_2_s_332", "particle_filename_1" : "7_va_2_s_350", "particle_filename_2" : "empty", "particle_filename_3" : "empty", "particle_filename_4" : "empty", "particle_layer_index_0" : 2, "particle_layer_index_1" : 2, "particle_layer_index_2" : 0, "particle_layer_index_3" : 0, "particle_layer_index_4" : 0, "particle_pos_x_0" : 0, "particle_pos_x_1" : 0, "particle_pos_x_2" : 0, "particle_pos_x_3" : 0, "particle_pos_x_4" : 0, "particle_pos_y_0" : 332, "particle_pos_y_1" : 350, "particle_pos_y_2" : 0, "particle_pos_y_3" : 0, "particle_pos_y_4" : 0, "particle_z_order_0" : 82, "particle_z_order_1" : 82, "particle_z_order_2" : 0, "particle_z_order_3" : 0, "particle_z_order_4" : 0, "sky_back_count" : 1, "sky_count" : 4, "sky_front_count" : 0, "sky_y" : 110.5, "type" : 39, "use_particle_count" : 2 }
, { "category" : 26, "class" : 0, "desc" : "니플헤임 - 2차 배경", "enable_divide_sky" : 1, "id" : 260000040, "kind" : 0, "map_name" : "niflheim_2", "particle_filename_0" : "8_ni_2_bf_-12", "particle_filename_1" : "8_ni_2_sf_188", "particle_filename_2" : "empty", "particle_filename_3" : "empty", "particle_filename_4" : "empty", "particle_layer_index_0" : 2, "particle_layer_index_1" : 2, "particle_layer_index_2" : 0, "particle_layer_index_3" : 0, "particle_layer_index_4" : 0, "particle_pos_x_0" : 0, "particle_pos_x_1" : 0, "particle_pos_x_2" : 0, "particle_pos_x_3" : 0, "particle_pos_x_4" : 0, "particle_pos_y_0" : -12, "particle_pos_y_1" : 188, "particle_pos_y_2" : 0, "particle_pos_y_3" : 0, "particle_pos_y_4" : 0, "particle_z_order_0" : 82, "particle_z_order_1" : 82, "particle_z_order_2" : 0, "particle_z_order_3" : 0, "particle_z_order_4" : 0, "sky_back_count" : 0, "sky_count" : 1, "sky_front_count" : 1, "sky_y" : 122.5, "type" : 40, "use_particle_count" : 2 }
, { "category" : 26, "class" : 0, "desc" : "아스가르드 - 2차 배경", "enable_divide_sky" : 1, "id" : 260000041, "kind" : 0, "map_name" : "asgard_2", "particle_filename_0" : "9_as_p_240", "particle_filename_1" : "empty", "particle_filename_2" : "empty", "particle_filename_3" : "empty", "particle_filename_4" : "empty", "particle_layer_index_0" : 2, "particle_layer_index_1" : 0, "particle_layer_index_2" : 0, "particle_layer_index_3" : 0, "particle_layer_index_4" : 0, "particle_pos_x_0" : 0, "particle_pos_x_1" : 0, "particle_pos_x_2" : 0, "particle_pos_x_3" : 0, "particle_pos_x_4" : 0, "particle_pos_y_0" : 240, "particle_pos_y_1" : 0, "particle_pos_y_2" : 0, "particle_pos_y_3" : 0, "particle_pos_y_4" : 0, "particle_z_order_0" : 82, "particle_z_order_1" : 0, "particle_z_order_2" : 0, "particle_z_order_3" : 0, "particle_z_order_4" : 0, "sky_back_count" : 2, "sky_count" : 1, "sky_front_count" : 1, "sky_y" : 102, "type" : 41, "use_particle_count" : 1 }
 ]